[
    {
        "id":0,
        "name": "zhuoziai",
        "position": [-55,750],
        "feature":"0100111",
        "Capacity":4
    },
    {
        "id" : 1,
        "name": "zhuoziai",
        "position": [250.0, 1200],
        "feature":"0000110",
        "Capacity":4
    },
    {
        "id" : 2,
        "name": "zhuozijiaoluo",
        "position": [520.0,1400],
        "feature":"0000111",
        "Capacity":2
    },
    {
        "id" : 3,
        "name": "zhuoziai",
        "position": [250.0,1200.0],
        "feature":"0000111",
        "Capacity":4
    },

    {
        "id":5,
        "name": "zhuozibar",
        "position": [100,1000],
        "feature":"1000111",
        "Capacity":2
    },
    {
        "id": 0,
        "name": "zhuozichuangbianlianzuo",
        "position": [-280, 420],
        "feature": "0100111",
        "Capacity": 6
    },
    {
        "id":6,
        "name": "zhuoziai",
        "position": [100,1050],
        "feature":"0100111",
        "Capacity":4
    },
    {
        "id": 8,
        "name": "zhuozizhongzhuo",
        "position": [-100, 350],
        "feature": "0000111",
        "Capacity": 3
    },
    {
        "id": 9,
        "name": "zhuozizhongjianchang",
        "position": [0, 0],
        "feature": "0000111",
        "Capacity": 6
    },
    {
        "id": 10,
        "name": "zhuozichuangbiandanzuo",
        "position": [-300, 350],
        "feature": "0000111",
        "Capacity": 6
    },
    {
        "id": 12,
        "name": "zhuozijiaoluozuobian",
        "position": [230, -220],
        "feature": "0100111",
        "Capacity": 3
    },
    {
        "id": 13,
        "name": "zhuozizhongjianzhongjianchuangbian",
        "position": [-210, 350],
        "feature": "0100111",
        "Capacity": 4
    },
    {
        "id": 14,
        "name": "zhuozizhongjianzhongjianchuangbian",
        "position": [-220, 200],
        "feature": "0100111",
        "Capacity": 4
    },
    {
        "id": 15,
        "name": "zhuozizhongjianzhongjianchuangbianxiao",
        "position": [-210, 80],
        "feature": "0100111",
        "Capacity": 2
    }
]
